genuity/__init__.py
genuity/compliance/__init__.py
genuity/compliance/compliance_check.py
genuity/core_generator/__init__.py
genuity/core_generator/differential_privacy.py
genuity/core_generator/copula/__init__.py
genuity/core_generator/copula/copula/__init__.py
genuity/core_generator/copula/copula/copula_core.py
genuity/core_generator/copula/utils/__init__.py
genuity/core_generator/copula/utils/api.py
genuity/core_generator/ctgan/__init__.py
genuity/core_generator/ctgan/ctgan/__init__.py
genuity/core_generator/ctgan/ctgan/config/__init__.py
genuity/core_generator/ctgan/ctgan/config/config.py
genuity/core_generator/ctgan/ctgan/models/__init__.py
genuity/core_generator/ctgan/ctgan/models/discriminator.py
genuity/core_generator/ctgan/ctgan/models/generator.py
genuity/core_generator/ctgan/ctgan/samplers/__init__.py
genuity/core_generator/ctgan/ctgan/samplers/sampler.py
genuity/core_generator/ctgan/ctgan/trainers/__init__.py
genuity/core_generator/ctgan/ctgan/trainers/trainer.py
genuity/core_generator/ctgan/ctgan/utils/__init__.py
genuity/core_generator/ctgan/ctgan/utils/api.py
genuity/core_generator/ctgan/ctgan/utils/factory.py
genuity/core_generator/ctgan/ctgan_premium/__init__.py
genuity/core_generator/ctgan/ctgan_premium/config/__init__.py
genuity/core_generator/ctgan/ctgan_premium/config/config.py
genuity/core_generator/ctgan/ctgan_premium/models/__init__.py
genuity/core_generator/ctgan/ctgan_premium/models/discriminator.py
genuity/core_generator/ctgan/ctgan_premium/models/generator.py
genuity/core_generator/ctgan/ctgan_premium/samplers/__init__.py
genuity/core_generator/ctgan/ctgan_premium/samplers/sampler.py
genuity/core_generator/ctgan/ctgan_premium/samplers/sampling_strategies.py
genuity/core_generator/ctgan/ctgan_premium/trainers/__init__.py
genuity/core_generator/ctgan/ctgan_premium/trainers/trainer.py
genuity/core_generator/ctgan/ctgan_premium/trainers/training_strategies.py
genuity/core_generator/ctgan/ctgan_premium/utils/__init__.py
genuity-1.0.0.dist-info/licenses/LICENSE
genuity-1.0.0.dist-info/METADATA
genuity-1.0.0.dist-info/WHEEL
genuity-1.0.0.dist-info/top_level.txt
genuity-1.0.0.dist-info/RECORD
