Metadata-Version: 2.4
Name: genuity
Version: 1.0.0
Summary: Genuity: A Unified Synthetic Data Library with Offline License Activation
Author: Genuity IO
License: Proprietary License
Project-URL: Homepage, https://github.com/genuity/genuity
Project-URL: Documentation, https://github.com/genuity/genuity
Project-URL: Repository, https://github.com/genuity/genuity
Project-URL: Issues, https://github.com/genuity/genuity/issues
Requires-Python: >=3.8
License-File: LICENSE
Dynamic: license-file
